midjourney_sdk_py/__init__.py
midjourney_sdk_py/main.py
midjourney_sdk_py-1.1.0.dist-info/LICENSE.md
midjourney_sdk_py-1.1.0.dist-info/METADATA
midjourney_sdk_py-1.1.0.dist-info/WHEEL
midjourney_sdk_py-1.1.0.dist-info/entry_points.txt
midjourney_sdk_py-1.1.0.dist-info/top_level.txt
midjourney_sdk_py-1.1.0.dist-info/RECORD
