Metadata-Version: 2.1
Name: midjourney-sdk-py
Version: 1.1.0
Summary: Midjourney SDK for interacting with Midjourney Discord. Get imagine. All options possible.
Home-page: https://github.com/reise69/Midjourney-sdk
Author: Alban Lamberet
Author-email: contact@refbax.com
License: MIT
Classifier: License :: OSI Approved :: MIT License
Classifier: Programming Language :: Python :: 3.8
Classifier: Programming Language :: Python :: 3.9
Classifier: Programming Language :: Python :: 3.10
License-File: LICENSE.md
Requires-Dist: requests
